model_w/project_maker/__init__.py
model_w/project_maker/__main__.py
model_w/project_maker/errors.py
model_w/project_maker/maker/__init__.py
model_w/project_maker/maker/_api.py
model_w/project_maker/maker/_base.py
model_w/project_maker/maker/_common.py
model_w/project_maker/maker/_front.py
model_w/project_maker/namer.py
model_w/project_maker/py.typed
model_w/project_maker/template/.editorconfig
model_w/project_maker/template/.formatignore
model_w/project_maker/template/.github/workflows/e2e.yml
model_w/project_maker/template/.gitignore
model_w/project_maker/template/.prettierrc
model_w/project_maker/template/README.md
model_w/project_maker/template/api/.dockerignore
model_w/project_maker/template/api/.env-template
model_w/project_maker/template/api/.env.test
model_w/project_maker/template/api/Dockerfile
model_w/project_maker/template/api/Dockerfile.test
model_w/project_maker/template/api/Makefile
model_w/project_maker/template/api/README.md
model_w/project_maker/template/api/___project_name__snake___/__init__.py
model_w/project_maker/template/api/___project_name__snake___/apps/__init__.py
model_w/project_maker/template/api/___project_name__snake___/apps/cms/README.md
model_w/project_maker/template/api/___project_name__snake___/apps/cms/__init__.py
model_w/project_maker/template/api/___project_name__snake___/apps/cms/api.py
model_w/project_maker/template/api/___project_name__snake___/apps/cms/blocks.py
model_w/project_maker/template/api/___project_name__snake___/apps/cms/demo.py
model_w/project_maker/template/api/___project_name__snake___/apps/cms/images/README.md
model_w/project_maker/template/api/___project_name__snake___/apps/cms/images/__tests__/test_serializers.py
model_w/project_maker/template/api/___project_name__snake___/apps/cms/images/blocks.py
model_w/project_maker/template/api/___project_name__snake___/apps/cms/images/models.py
model_w/project_maker/template/api/___project_name__snake___/apps/cms/images/serializers.py
modelw_project_maker-2026.1.0.dist-info/METADATA
modelw_project_maker-2026.1.0.dist-info/WHEEL
modelw_project_maker-2026.1.0.dist-info/entry_points.txt
modelw_project_maker-2026.1.0.dist-info/RECORD
