Metadata-Version: 2.4
Name: modelw-project-maker
Version: 2026.1.0
Summary: A tool to create Model-W-compliant projects
License: WTFPL
Keywords: model-w,django,nuxt,boilerplate,template
Author: Rémy Sanchez
Author-email: remy.sanchez@hyperthese.net
Requires-Python: >=3.14,<4.0
Classifier: Development Status :: 4 - Beta
Classifier: Environment :: Console
Classifier: Intended Audience :: Developers
Classifier: License :: Other/Proprietary License
Classifier: Programming Language :: Python :: 3
Classifier: Programming Language :: Python :: 3.14
Classifier: Topic :: Software Development :: Code Generators
Classifier: Topic :: Utilities
Requires-Dist: Unidecode (>=1.4.0,<2.0.0)
Requires-Dist: black (>=23,<24)
Requires-Dist: isort (>=5.13.2,<6.0.0)
Requires-Dist: monoformat (>=0.2.0,<0.3.0)
Requires-Dist: node-edge (>=0.1.0b2,<0.2.0)
Requires-Dist: pathspec (>=0.11,<0.12)
Requires-Dist: rich (>=14.2.0,<15.0.0)
Requires-Dist: setuptools
Requires-Dist: tomlkit (>=0.13.3,<0.14.0)
Project-URL: Documentation, https://github.com/ModelW/project-maker
Project-URL: Homepage, https://github.com/ModelW/project-maker
Project-URL: Repository, https://github.com/ModelW/project-maker
